{
  "project_info": {
    "project_number": "773497788962",
    "project_id": "productcataloglab5-62f94",
    "storage_bucket": "productcataloglab5-62f94.appspot.com"
  },
  "client": [
    {
      "client_info": {
        "mobilesdk_app_id": "1:773497788962:android:7a5430ad188935f00cc87b",
        "android_client_info": {
          "package_name": "com.example.productcataloglab5"
        }
      },
      "oauth_client": [],
      "api_key": [
        {
          "current_key": "AIzaSyB7nZ2s3WfAel5gismOcOfD1BHPK_72qJA"
        }
      ],
      "services": {
        "appinvite_service": {
          "other_platform_oauth_client": []
        }
      }
    }
  ],
  "configuration_version": "1"
}